securepickle/__init__.py
securepickle/securepickle.py
securepickle-0.0.0.dist-info/METADATA
securepickle-0.0.0.dist-info/WHEEL
securepickle-0.0.0.dist-info/top_level.txt
securepickle-0.0.0.dist-info/RECORD
