Metadata-Version: 2.1
Name: securepickle
Version: 0.0.0
Summary: Tools for secured pickling
Home-page: https://github.com/goncalopp/securepickle
License: UNKNOWN
Platform: UNKNOWN
Classifier: Programming Language :: Python :: 3
Classifier: Programming Language :: Python :: 2
Classifier: Operating System :: OS Independent
